ftea/__init__.py
ftea/_tea.c
ftea/_tea.cp314t-win_arm64.pyd
ftea/_tea.pyi
ftea/_tea.pyx
ftea/_xtea.c
ftea/_xtea.cp314t-win_arm64.pyd
ftea/_xtea.pyx
ftea/tea.pxd
ftea/xtea.pxd
ftea-0.1.10.dist-info/METADATA
ftea-0.1.10.dist-info/WHEEL
ftea-0.1.10.dist-info/top_level.txt
ftea-0.1.10.dist-info/RECORD
