Metadata-Version: 2.1
Name: ftea
Version: 0.1.10
Summary: tea encrypt and decrypt
Home-page: https://github.com/synodriver/ftea
Author: synodriver
Author-email: diguohuangjiajinweijun@gmail.com
License: BSD
Keywords: tea
Classifier: Development Status :: 4 - Beta
Classifier: Operating System :: OS Independent
Classifier: License :: OSI Approved :: BSD License
Classifier: Programming Language :: C
Classifier: Programming Language :: Cython
Classifier: Programming Language :: Python
Classifier: Programming Language :: Python :: 3.8
Classifier: Programming Language :: Python :: 3.9
Classifier: Programming Language :: Python :: 3.10
Classifier: Programming Language :: Python :: 3.11
Classifier: Programming Language :: Python :: 3.12
Classifier: Programming Language :: Python :: 3.13
Classifier: Programming Language :: Python :: Implementation :: CPython
Requires-Python: >=3.6
